pynpr
