Metadata-Version: 1.0
Name: pynpr
Version: 0.2.2
Summary: unofficial NPR api
Home-page: https://github.com/JarbasAl/pynpr
Author: jarbasAI
Author-email: jarbasai@mailfence.com
License: MIT
Keywords: public,radio,stream,metadata,api,service,npr
Platform: UNKNOWN
